CachedFileDic/__init__.py
CachedFileDic/test.py
CachedFileDic-0.3.0.dist-info/METADATA
CachedFileDic-0.3.0.dist-info/WHEEL
CachedFileDic-0.3.0.dist-info/top_level.txt
CachedFileDic-0.3.0.dist-info/RECORD
