Metadata-Version: 2.1
Name: CachedFileDic
Version: 0.3.0
Summary: Fast Dictionary-Type Database
Home-page: https://github.co.jp/
Author: bib_inf
Author-email: contact.bibinf@gmail.com
License: CC0 v1.0
Classifier: Programming Language :: Python :: 3
Classifier: License :: CC0 1.0 Universal (CC0 1.0) Public Domain Dedication
Requires-Dist: ezpip
Requires-Dist: sout (>=1.2.1)
Requires-Dist: relpath
Requires-Dist: fies (>=1.4.0)
